mystix/__init__.py
mystix/__main__.py
mystix/language/__init__.py
mystix/language/example.py
mystix/language/evaluation/__init__.py
mystix/language/evaluation/errors.py
mystix/language/evaluation/evaluator.py
mystix/language/evaluation/main.py
mystix/language/evaluation/vars.py
mystix/language/parsing/__init__.py
mystix/language/parsing/parser.py
mystix/language/shared/__init__.py
mystix/language/shared/ast/Body.py
mystix/language/shared/ast/Declare.py
mystix/language/shared/ast/Node.py
mystix/language/shared/ast/Program.py
mystix/language/shared/ast/Source.py
mystix/language/shared/ast/Type.py
mystix/language/shared/ast/Value.py
mystix/language/shared/ast/Var.py
mystix/language/shared/ast/__init__.py
mystix/language/shared/ast/visitor.py
mystix/language/shared/ast/commands_ast/Assigner.py
mystix/language/shared/ast/commands_ast/Command.py
mystix/language/shared/ast/commands_ast/Loader.py
mystix/language/shared/ast/commands_ast/Mapper.py
mystix/language/shared/ast/commands_ast/Plotter.py
mystix/language/shared/ast/commands_ast/Trigger.py
mystix/language/shared/ast/commands_ast/__init__.py
mystix/language/shared/ast/graphs_ast/Axis.py
mystix/language/shared/ast/graphs_ast/Graph.py
mystix/language/shared/ast/graphs_ast/__init__.py
mystix/language/shared/ast/math_ast/BuiltinFunc.py
mystix/language/shared/ast/math_ast/FastFunc.py
mystix/language/shared/ast/math_ast/Func.py
mystix/language/shared/ast/math_ast/MathFuncs.py
mystix/language/shared/ast/math_ast/Operand.py
mystix/language/shared/ast/math_ast/SimpleFunc.py
mystix/language/shared/ast/math_ast/__init__.py
mystix/language/shared/primitives/__init__.py
mystix/language/shared/primitives/graphs.py
mystix/language/shared/primitives/numerical.py
mystix/language/shared/primitives/types.py
mystix/language/shared/primitives/values.py
mystix/language/tokenization/__init__.py
mystix/language/tokenization/tokenizer.py
mystix/targets/__init__.py
mystix/targets/analysis/__init__.py
mystix/targets/analysis/math.py
mystix-0.1.5.dist-info/LICENSE
mystix-0.1.5.dist-info/METADATA
mystix-0.1.5.dist-info/WHEEL
mystix-0.1.5.dist-info/top_level.txt
mystix-0.1.5.dist-info/RECORD
