Metadata-Version: 2.1
Name: mystix
Version: 0.1.5
Summary: A domain-specific language intended for event-driven acquisition, analysis, and visualization of data.
Home-page: UNKNOWN
Author: Rowan Lindsay
Author-email: development@rowanlindsay.com
License: UNKNOWN
Platform: UNKNOWN
Requires-Python: >=3.8
Requires-Dist: numpy
Requires-Dist: seaborn
Requires-Dist: matplotlib
Requires-Dist: pyqtgraph
Requires-Dist: pyqt5
Requires-Dist: mypy
Requires-Dist: requests
Requires-Dist: flask
